[
  {
    "ContainingType": "projectApiAngular.Controllers.CategoryController",
    "Method": "GetAllCategories",
    "RelativePath": "api/Category",
    "HttpMethod": "GET",
    "IsController": true,
    "Order": 0,
    "Parameters": [],
    "ReturnTypes": []
  },
  {
    "ContainingType": "projectApiAngular.Controllers.CategoryController",
    "Method": "AddCategory",
    "RelativePath": "api/Category",
    "HttpMethod": "POST",
    "IsController": true,
    "Order": 0,
    "Parameters": [
      {
        "Name": "category",
        "Type": "projectApiAngular.DTO.CategoryDto\u002BCreateCategoryDto",
        "IsRequired": true
      }
    ],
    "ReturnTypes": []
  },
  {
    "ContainingType": "projectApiAngular.Controllers.CategoryController",
    "Method": "DeleteCategory",
    "RelativePath": "api/Category/{id}",
    "HttpMethod": "DELETE",
    "IsController": true,
    "Order": 0,
    "Parameters": [
      {
        "Name": "id",
        "Type": "System.Int32",
        "IsRequired": true
      }
    ],
    "ReturnTypes": []
  },
  {
    "ContainingType": "projectApiAngular.Controllers.CategoryController",
    "Method": "UpdateCategory",
    "RelativePath": "api/Category/{id}",
    "HttpMethod": "PUT",
    "IsController": true,
    "Order": 0,
    "Parameters": [
      {
        "Name": "id",
        "Type": "System.Int32",
        "IsRequired": true
      },
      {
        "Name": "category",
        "Type": "projectApiAngular.DTO.CategoryDto\u002BCreateCategoryDto",
        "IsRequired": true
      }
    ],
    "ReturnTypes": []
  },
  {
    "ContainingType": "projectApiAngular.Controllers.DonnerController",
    "Method": "GetAllDonners",
    "RelativePath": "api/Donner",
    "HttpMethod": "GET",
    "IsController": true,
    "Order": 0,
    "Parameters": [],
    "ReturnTypes": []
  },
  {
    "ContainingType": "projectApiAngular.Controllers.DonnerController",
    "Method": "AddDonner",
    "RelativePath": "api/Donner",
    "HttpMethod": "POST",
    "IsController": true,
    "Order": 0,
    "Parameters": [
      {
        "Name": "dto",
        "Type": "projectApiAngular.DTO.DonnerDto\u002BCreateDonnerDto",
        "IsRequired": true
      }
    ],
    "ReturnTypes": []
  },
  {
    "ContainingType": "projectApiAngular.Controllers.DonnerController",
    "Method": "GetDonnerById",
    "RelativePath": "api/Donner/{id}",
    "HttpMethod": "GET",
    "IsController": true,
    "Order": 0,
    "Parameters": [
      {
        "Name": "id",
        "Type": "System.Int32",
        "IsRequired": true
      }
    ],
    "ReturnTypes": []
  },
  {
    "ContainingType": "projectApiAngular.Controllers.DonnerController",
    "Method": "DeleteDonner",
    "RelativePath": "api/Donner/{id}",
    "HttpMethod": "DELETE",
    "IsController": true,
    "Order": 0,
    "Parameters": [
      {
        "Name": "id",
        "Type": "System.Int32",
        "IsRequired": true
      }
    ],
    "ReturnTypes": []
  },
  {
    "ContainingType": "projectApiAngular.Controllers.DonnerController",
    "Method": "UpdateDonner",
    "RelativePath": "api/Donner/{id}",
    "HttpMethod": "PUT",
    "IsController": true,
    "Order": 0,
    "Parameters": [
      {
        "Name": "id",
        "Type": "System.Int32",
        "IsRequired": true
      },
      {
        "Name": "dto",
        "Type": "projectApiAngular.DTO.DonnerDto\u002BUpdateDonnerDto",
        "IsRequired": true
      }
    ],
    "ReturnTypes": []
  },
  {
    "ContainingType": "projectApiAngular.Controllers.DonnerController",
    "Method": "GetDonnerByEmail",
    "RelativePath": "api/Donner/byemail",
    "HttpMethod": "GET",
    "IsController": true,
    "Order": 0,
    "Parameters": [
      {
        "Name": "email",
        "Type": "System.String",
        "IsRequired": false
      }
    ],
    "ReturnTypes": []
  },
  {
    "ContainingType": "projectApiAngular.Controllers.DonnerController",
    "Method": "GetDonnerByGiftId",
    "RelativePath": "api/Donner/bygift/{giftId}",
    "HttpMethod": "GET",
    "IsController": true,
    "Order": 0,
    "Parameters": [
      {
        "Name": "giftId",
        "Type": "System.Int32",
        "IsRequired": true
      }
    ],
    "ReturnTypes": []
  },
  {
    "ContainingType": "projectApiAngular.Controllers.DonnerController",
    "Method": "GetDonnerByName",
    "RelativePath": "api/Donner/byname/{name}",
    "HttpMethod": "GET",
    "IsController": true,
    "Order": 0,
    "Parameters": [
      {
        "Name": "name",
        "Type": "System.String",
        "IsRequired": true
      }
    ],
    "ReturnTypes": []
  },
  {
    "ContainingType": "projectApiAngular.Controllers.GiftController",
    "Method": "GetAllGifts",
    "RelativePath": "api/Gift",
    "HttpMethod": "GET",
    "IsController": true,
    "Order": 0,
    "Parameters": [],
    "ReturnTypes": []
  },
  {
    "ContainingType": "projectApiAngular.Controllers.GiftController",
    "Method": "Addgift",
    "RelativePath": "api/Gift",
    "HttpMethod": "POST",
    "IsController": true,
    "Order": 0,
    "Parameters": [
      {
        "Name": "gift",
        "Type": "projectApiAngular.DTO.GiftDto\u002BCreateGiftDto",
        "IsRequired": true
      }
    ],
    "ReturnTypes": []
  },
  {
    "ContainingType": "projectApiAngular.Controllers.GiftController",
    "Method": "DeleteGift",
    "RelativePath": "api/Gift/{id}",
    "HttpMethod": "DELETE",
    "IsController": true,
    "Order": 0,
    "Parameters": [
      {
        "Name": "id",
        "Type": "System.Int32",
        "IsRequired": true
      }
    ],
    "ReturnTypes": []
  },
  {
    "ContainingType": "projectApiAngular.Controllers.GiftController",
    "Method": "UpdateGift",
    "RelativePath": "api/Gift/{id}",
    "HttpMethod": "PUT",
    "IsController": true,
    "Order": 0,
    "Parameters": [
      {
        "Name": "name",
        "Type": "System.String",
        "IsRequired": false
      },
      {
        "Name": "gift",
        "Type": "projectApiAngular.DTO.GiftDto\u002BUpdateGiftDto",
        "IsRequired": true
      },
      {
        "Name": "id",
        "Type": "",
        "IsRequired": true
      }
    ],
    "ReturnTypes": []
  },
  {
    "ContainingType": "projectApiAngular.Controllers.GiftController",
    "Method": "GetGiftByName",
    "RelativePath": "api/Gift/{name}",
    "HttpMethod": "GET",
    "IsController": true,
    "Order": 0,
    "Parameters": [
      {
        "Name": "name",
        "Type": "System.String",
        "IsRequired": true
      }
    ],
    "ReturnTypes": []
  },
  {
    "ContainingType": "projectApiAngular.Controllers.GiftController",
    "Method": "GetGiftByDonnerName",
    "RelativePath": "api/Gift/doner/{name}",
    "HttpMethod": "GET",
    "IsController": true,
    "Order": 0,
    "Parameters": [
      {
        "Name": "name",
        "Type": "System.String",
        "IsRequired": true
      }
    ],
    "ReturnTypes": []
  },
  {
    "ContainingType": "projectApiAngular.Controllers.GiftController",
    "Method": "GetbyNumCastomer",
    "RelativePath": "api/Gift/numcustomer/{count}",
    "HttpMethod": "GET",
    "IsController": true,
    "Order": 0,
    "Parameters": [
      {
        "Name": "count",
        "Type": "System.Int32",
        "IsRequired": true
      }
    ],
    "ReturnTypes": []
  }
]